{
  "items": [
    {
      "position": 4,
      "path": "I:\\Picture\\Wallpaper\\sexy girl.png"
    },
    {
      "position": 4,
      "path": "I:\\Picture\\Wallpaper\\sexy2.jpg"
    },
    {
      "position": 4,
      "path": "I:\\Picture\\Wallpaper\\甘雨.jpg"
    },
    {
      "position": 4,
      "path": "I:\\Picture\\Wallpaper\\梦璃.jpg"
    },
    {
      "position": 4,
      "path": "I:\\Picture\\Wallpaper\\天使.jpg"
    },
    {
      "position": 4,
      "path": "I:\\Picture\\Wallpaper\\胸.jpg"
    }
  ],
  "current": {
    "position": 4,
    "path": "I:\\Picture\\Wallpaper\\sexy girl.png"
  }
}